MANIFEST.in
README.rst
licence.txt
setup.py
RegexTester.egg-info/PKG-INFO
RegexTester.egg-info/SOURCES.txt
RegexTester.egg-info/dependency_links.txt
RegexTester.egg-info/requires.txt
RegexTester.egg-info/top_level.txt
regex_tester/__init__.py
regex_tester/core.py
regex_tester/parallel.py
regex_tester/regex_tester
regex_tester/libs/__init__.py
regex_tester/libs/bottle.py
regex_tester/libs/clize.py
regex_tester/static/behavior.js
regex_tester/static/jquery.js
regex_tester/static/screen.css
regex_tester/static/style.css
regex_tester/views/index.tpl