Metadata-Version: 1.1
Name: RegexTester
Version: 0.5
Summary: Python online regex tester for Python 2.7+
Home-page: https://github.com/ksamuel/Python-regex-tester
Author: Kevin Samuel
Author-email: kevin@yeleman.com
License: UNKNOWN
Platform: UNKNOWN
Classifier: Programming Language :: Python
